autosubtitle/__init__.py
autosubtitle/client.py
autosubtitle/errors.py
autosubtitle_api-1.0.1.dist-info/licenses/LICENSE
autosubtitle_api-1.0.1.dist-info/METADATA
autosubtitle_api-1.0.1.dist-info/WHEEL
autosubtitle_api-1.0.1.dist-info/top_level.txt
autosubtitle_api-1.0.1.dist-info/RECORD
