Metadata-Version: 2.4
Name: autosubtitle-api
Version: 1.0.1
Summary: Official Python client library for AutoSubtitle.net API
Author-email: AutoSubtitle <info@berkbirkan.com>
License: MIT
Project-URL: Homepage, https://autosubtitle.net
Project-URL: Documentation, https://autosubtitle.net/docs
Keywords: autosubtitle,subtitles,video,transcription,api,client
Classifier: Development Status :: 4 - Beta
Classifier: Intended Audience :: Developers
Classifier: License :: OSI Approved :: MIT License
Classifier: Programming Language :: Python :: 3
Classifier: Programming Language :: Python :: 3.8
Classifier: Programming Language :: Python :: 3.9
Classifier: Programming Language :: Python :: 3.10
Classifier: Programming Language :: Python :: 3.11
Classifier: Programming Language :: Python :: 3.12
Requires-Python: >=3.8
License-File: LICENSE
Requires-Dist: requests>=2.28.0
Dynamic: license-file
